opsmith/__init__.py
opsmith/agent.py
opsmith/constants.py
opsmith/exceptions.py
opsmith/git_repo.py
opsmith/main.py
opsmith/models.py
opsmith/prompts.py
opsmith/repo_map.py
opsmith/service_detector.py
opsmith/settings.py
opsmith/types.py
opsmith/utils.py
opsmith/cloud_providers/__init__.py
opsmith/cloud_providers/aws.py
opsmith/cloud_providers/base.py
opsmith/cloud_providers/gcp.py
opsmith/deployment_strategies/__init__.py
opsmith/deployment_strategies/base.py
opsmith/deployment_strategies/monolithic.py
opsmith/infra_provisioners/__init__.py
opsmith/infra_provisioners/ansible_provisioner.py
opsmith/infra_provisioners/base_provisioner.py
opsmith/infra_provisioners/terraform_provisioner.py
opsmith/queries/tree-sitter-languages/README.md
opsmith/queries/tree-sitter-languages/arduino-tags.scm
opsmith/queries/tree-sitter-languages/c-tags.scm
opsmith/queries/tree-sitter-languages/c_sharp-tags.scm
opsmith/queries/tree-sitter-languages/chatito-tags.scm
opsmith/queries/tree-sitter-languages/commonlisp-tags.scm
opsmith/queries/tree-sitter-languages/cpp-tags.scm
opsmith/queries/tree-sitter-languages/csharp-tags.scm
opsmith/queries/tree-sitter-languages/d-tags.scm
opsmith/queries/tree-sitter-languages/dart-tags.scm
opsmith/queries/tree-sitter-languages/elisp-tags.scm
opsmith/queries/tree-sitter-languages/elixir-tags.scm
opsmith/queries/tree-sitter-languages/elm-tags.scm
opsmith/queries/tree-sitter-languages/gleam-tags.scm
opsmith/queries/tree-sitter-languages/go-tags.scm
opsmith/queries/tree-sitter-languages/hcl-tags.scm
opsmith/queries/tree-sitter-languages/java-tags.scm
opsmith/queries/tree-sitter-languages/javascript-tags.scm
opsmith/queries/tree-sitter-languages/kotlin-tags.scm
opsmith/queries/tree-sitter-languages/lua-tags.scm
opsmith/queries/tree-sitter-languages/ocaml-tags.scm
opsmith/queries/tree-sitter-languages/ocaml_interface-tags.scm
opsmith/queries/tree-sitter-languages/php-tags.scm
opsmith/queries/tree-sitter-languages/pony-tags.scm
opsmith_cli-0.4.3b0.dist-info/METADATA
opsmith_cli-0.4.3b0.dist-info/WHEEL
opsmith_cli-0.4.3b0.dist-info/entry_points.txt
opsmith_cli-0.4.3b0.dist-info/licenses/LICENSE.txt
opsmith_cli-0.4.3b0.dist-info/RECORD
