Metadata-Version: 2.4
Name: opsmith-cli
Version: 0.4.3b0
Summary: Opsmith is an AI devops engineer in your terminal
License-Expression: GPL-3.0-only
License-File: LICENSE.txt
Classifier: Development Status :: 4 - Beta
Classifier: Environment :: Console
Classifier: Intended Audience :: Developers
Classifier: Programming Language :: Python
Classifier: Programming Language :: Python :: 3
Classifier: Programming Language :: Python :: 3.10
Classifier: Programming Language :: Python :: 3.11
Classifier: Programming Language :: Python :: 3.12
Classifier: Programming Language :: Python :: 3.13
Classifier: Topic :: Software Development
Requires-Python: >=3.11
Requires-Dist: ansible==12.3.0
Requires-Dist: gitpython==3.1.45
Requires-Dist: google-api-python-client==2.187.0
Requires-Dist: google-cloud-compute==1.40.0
Requires-Dist: google-cloud-resource-manager==1.15.0
Requires-Dist: google-cloud-storage==3.7.0
Requires-Dist: grep-ast==0.9.0
Requires-Dist: inquirer==3.4.1
Requires-Dist: jinja2==3.1.6
Requires-Dist: networkx==3.6.1
Requires-Dist: pick==2.4.0
Requires-Dist: pydantic-ai==1.37.0
Requires-Dist: pydantic==2.12.5
Requires-Dist: python-dotenv==1.2.1
Requires-Dist: pyyaml==6.0.3
Requires-Dist: tqdm==4.67.1
Requires-Dist: tree-sitter-language-pack==0.13.0
Requires-Dist: typer==0.20.1
